questions_three_aws/__init__.py
questions_three_aws/module_cfg.yml
questions_three_aws/s3_artifact_saver/__init__.py
questions_three_aws/s3_artifact_saver/s3_artifact_saver.py
questions_three_aws-3.12.0.0.dist-info/METADATA
questions_three_aws-3.12.0.0.dist-info/WHEEL
questions_three_aws-3.12.0.0.dist-info/top_level.txt
questions_three_aws-3.12.0.0.dist-info/RECORD
