Metadata-Version: 2.1
Name: questions-three-aws
Version: 3.12.0.0
Summary: Amazon Web Services integrations for Questions Three
Home-page: https://github.com/CyberGRX/questions-three
Author: Mike Duskis
Author-email: mike.duskis@cybergrx.com
License: UNKNOWN
Platform: UNKNOWN
Classifier: Development Status :: 5 - Production/Stable
Classifier: Intended Audience :: Developers
Classifier: License :: OSI Approved :: MIT License
Classifier: Natural Language :: English
Classifier: Operating System :: OS Independent
Classifier: Programming Language :: Python :: 3
Classifier: Topic :: Software Development :: Testing
Requires-Dist: boto3 (>=1.10.4)
Requires-Dist: docutils (<0.15,>=0.10)
Requires-Dist: expects (>=0.8.0)
Requires-Dist: pyfakefs (>=3.4.3)
Requires-Dist: questions-three
Requires-Dist: twin-sister (>=4.5.1)
Requires-Dist: twine (>=1.9.1)
Requires-Dist: wheel (>=0.30.0)
